{"timestamp":"2026-04-26T13:12:23.023425+00:00","nfs":{"nrf":{"container_status":"running","reachable":false,"latest_latency_ms":7.01,"anomaly_score":0.0,"candidate_rank":1},"amf":{"container_status":"running","reachable":false,"latest_latency_ms":4.48,"anomaly_score":0.0,"candidate_rank":2},"smf":{"container_status":"running","reachable":false,"latest_latency_ms":2.47,"anomaly_score":0.0,"candidate_rank":3},"pcf":{"container_status":"running","reachable":false,"latest_latency_ms":4.76,"anomaly_score":0.0,"candidate_rank":4},"udm":{"container_status":"running","reachable":false,"latest_latency_ms":2.62,"anomaly_score":0.0,"candidate_rank":5},"udr":{"container_status":"running","reachable":true,"latest_latency_ms":2.31,"anomaly_score":0.0,"candidate_rank":7},"ausf":{"container_status":"running","reachable":true,"latest_latency_ms":2.18,"anomaly_score":0.0,"candidate_rank":8},"nssf":{"container_status":"running","reachable":true,"latest_latency_ms":2.31,"anomaly_score":0.0,"candidate_rank":6}}}